[{
        "index": 1,
        "title": "绵柔酱香",
        "src": "http://img0.gjw.com/Famous/2019/0803/38d2e219ae91448699505554ebeb2c68.jpg",
        "text": "51度 茅台 汉酱酒 （ 2018年产 ）500ml ",
        "price": "299 元"
    }, {
        "index": 2,
        "title": "韵味悠长",
        "src": "http://img0.gjw.com/Famous/2019/0803/c9cb6f4f854c4d4996ec675a251bbf6b.jpg",
        "text": "53度 茅台 贵州大曲酒 80年代 金酱 （ 2018年产 ）500ml ",
        "price": "159 元"
    }, {
        "index": 3,
        "title": "买一送一",
        "src": "http://img0.gjw.com/Famous/2019/0803/894f98012d4c4561a87042737022163f.jpg",
        "text": "53度 茅台王子 酱香经典 （ 2018年产 ） 500ml ",
        "price": "439 元"
    }, {
        "index": 4,
        "title": "己亥猪年",
        "src": "http://img0.gjw.com/Famous/2019/0803/e1ba1079e3b544cc8329bf4fd16da6f6.jpg",
        "text": "【整箱装】53度 茅台王子 己亥猪年酒 500ml*6瓶 ",
        "price": "2940 元"
    }, {
        "index": 5,
        "title": "端午踩曲",
        "src": "http://img0.gjw.com/Famous/2019/0803/d1b03b1600354124960f83b8da0dc0c1.jpg",
        "text": "53度 茅台 赖茅酒（端曲）（ 2016年产 ）500ml ",
        "price": "169 元"
    }, {
        "index": 6,
        "title": "醇香记忆",
        "src": "http://img0.gjw.com/Famous/2019/0803/de32579ef17249329623d7a1dfa009ee.jpg",
        "text": "53度 茅台 贵州大曲酒 70年代 （ 2019年产 ）500ml ",
        "price": "239 元"
    }, {
        "index": 7,
        "title": "买一送一",
        "src": "http://img0.gjw.com/Famous/2019/0803/715ebe86d4cd4023ad30c27498f50890.jpg",
        "text": "53度 茅台 珍品王子酒 （ 2018年产 ）500ml ",
        "price": "419 元"
    }, {
        "index": 8,
        "title": "中国红",
        "src": "http://img0.gjw.com/Famous/2019/0803/35deebc486614c03b25c40d71b3a3e96.jpg",
        "text": "【整箱装】53度 茅台迎宾（中国红）（ 2017年产）500ml*6瓶 ",
        "price": "529 元"
    },




    {
        "index": 9,
        "title": "空杯留香",
        "src": "http://img0.gjw.com/Famous/2019/0803/04557886fcf347e1bc20b922af0caf7d.jpg",
        "text": "53度 茅台 珍品王子酒 （ 2011年产 ）1000ml ",
        "price": "699 元"
    }, {
        "index": 10,
        "title": "百善孝先",
        "src": "http://img0.gjw.com/Famous/2019/0803/2eb1a784ca98420b9975a012f5b24302.jpg",
        "text": "53度 茅台 孝道酒 （ 2017年产 ）500ml ",
        "price": "259 元"
    }, {
        "index": 11,
        "title": "五粮老酒",
        "src": "http://img0.gjw.com/Famous/2019/0803/75e3b6194645490da1d42dd3a84f9b84.jpg",
        "text": "53度 五粮液股份 永福酱酒（老酱）（2010-2012年产）500ml ",
        "price": "479 元"
    }, {
        "index": 12,
        "title": "东方习酒",
        "src": "http://img0.gjw.com/Famous/2019/0803/316198c5a25b412c970011126442acce.jpg",
        "text": "53度 习酒 窖藏 1988（2012年产）500ml ",
        "price": "799 元"
    }, {
        "index": 13,
        "title": "精品特曲",
        "src": "http://img0.gjw.com/Famous/2019/0803/afb1a043ced546d6b7efd6fc0d2840fc.jpg",
        "text": "52度 泸州老窖 精品特曲 限量珍藏版 （ 2010年产 ）500ml ",
        "price": "319 元"
    }, {
        "index": 14,
        "title": "新郎酒",
        "src": "http://img0.gjw.com/Famous/2019/0803/b6afb4989dbf4f6bb473fa6974a33277.jpg",
        "text": "52度 郎酒 12年陈 新郎酒 （ 2011年产 ）500ml ",
        "price": "419 元"
    }, {
        "index": 15,
        "title": "祥瑞之酒",
        "src": "http://img0.gjw.com/Famous/2019/0803/37f5bf293f044487aafbdbbd84234cd4.jpg",
        "text": "52度 国窖 1573 鸿运568（2016年产） 500ml ",
        "price": "专属会员价 元"
    }, {
        "index": 16,
        "title": "五粮源酒",
        "src": "http://img0.gjw.com/Famous/2019/0803/35f7587b453d4e19bd03af4fb715507a.jpg",
        "text": "52度 五粮液股份 五粮源 精品酒 （2012年产）500ml ",
        "price": "89 元"
    },





    {
        "index": 17,
        "title": "八年陈酿",
        "src": "http://img0.gjw.com/Famous/2019/0803/d8636d808c51426f81b1299817e7cf7d.jpg",
        "text": "53度珍酒珍八500ml  ",
        "price": "专属会员价100 元"
    }, {
        "index": 18,
        "title": "口感醇和",
        "src": "http://img0.gjw.com/Famous/2019/0803/8321e70339ff4acba532aed720ca90b1.jpg",
        "text": "52度洋河梦之蓝（M9）500ml ",
        "price": "1299 元"
    }, {
        "index": 19,
        "title": "买一送一",
        "src": "http://img0.gjw.com/Famous/2019/0803/561564cca5644ec9b31921abd22ee1ea.jpg",
        "text": "53度汾酒青花20年500ml  ",
        "price": "578 元"
    }, {
        "index": 20,
        "title": "买一送一",
        "src": "http://img0.gjw.com/Famous/2019/0803/66d9571eb5de4ff782c947a501933168.jpg",
        "text": "54度董酒国密畅享10 500ml ",
        "price": "369 元"
    }, {
        "index": 21,
        "title": "金装糊涂",
        "src": "http://img0.gjw.com/Famous/2019/0803/de016648f36e4a04bf4c335a951504ca.jpg",
        "text": "52度金装糊涂酒500ml  ",
        "price": "98 元"
    }, {
        "index": 22,
        "title": "系出名门",
        "src": "http://img0.gjw.com/Famous/2019/0803/74f77e12a4e04cd184cf823ecae2ac57.jpg",
        "text": "52度五粮液股份公司1995专卖店酒（新） 500ml",
        "price": "228 元"
    }, {
        "index": 23,
        "title": "复古特曲",
        "src": "http://img0.gjw.com/Famous/2019/0803/f3e64cb6f25f47a184661876d130f9ae.jpg",
        "text": "52度泸州老窖特曲（60版）500ml",
        "price": "459 元"
    }, {
        "index": 24,
        "title": "传世千年",
        "src": "http://img0.gjw.com/Famous/2019/0803/5f86efbbc99c42418621a4d71999bd15.jpg",
        "text": "52度西凤凤香经典10年500ml",
        "price": "159 元"
    },







    {
        "index": 25,
        "title": "一级庄",
        "src": "http://img0.gjw.com/Famous/2019/0803/86a3a829b5364b4e815cfa47df366592.jpg",
        "text": "法国 苏玳一级庄 拉菲莱斯珍宝贵腐甜白葡萄酒 2015 750ml\t\t ",
        "price": "248 元"
    }, {
        "index": 26,
        "title": "珍藏佳酿",
        "src": "http://img0.gjw.com/Famous/2019/0803/22e989dc6b674394b6a90f9328ea601f.jpg",
        "text": "中国 长城 桑干酒庄 珍藏级 赤霞珠梅洛 红葡萄酒750ml\t\t ",
        "price": "328 元"
    }, {
        "index": 27,
        "title": "立减100元",
        "src": "http://img0.gjw.com/Famous/2019/0803/ccb164a1127b4a3e82eb5792fc569171.jpg",
        "text": "澳大利亚 凯斯勒 石马设拉子 红葡萄酒 750ml\t\t ",
        "price": "268 元"
    }, {
        "index": 28,
        "title": "整箱559元",
        "src": "http://img0.gjw.com/Famous/2019/0803/8c06ba1db1f048e880ce21f17c3478f1.jpg",
        "text": "法国 中级庄 梅多克贝桥 佩桥城堡 Chateau Pey De Pont 红葡萄酒 750ml*6【整箱装】\t\t ",
        "price": "559 元"
    },





    {
        "index": 29,
        "title": "整箱囤起",
        "src": "http://img0.gjw.com/Famous/2019/0803/59c75507129d43859bcde3078e54bc9c.jpg",
        "text": "德国 德森森 兰贵人 半甜白葡萄酒 750ml*6瓶【整箱装】\t\t ",
        "price": "199 元"
    }, {
        "index": 30,
        "title": "立减100元",
        "src": "http://img0.gjw.com/Famous/2019/0803/502a58b60a0647a6ac081ecc13df102b.jpg",
        "text": "澳大利亚 奔富 洛神山庄 西拉赤霞珠 红葡萄酒 1500ml\t\t ",
        "price": "199 元"
    }, {
        "index": 31,
        "title": "到手两瓶",
        "src": "",
        "text": "法国 拉菲 奥希耶西慕 红葡萄酒 750ml\t\t ",
        "price": "196 元"
    }, {
        "index": 32,
        "title": "整箱嗨购",
        "src": "http://img0.gjw.com/Famous/2019/0803/37897e34c73c4ceb962984c256326ceb.jpg",
        "text": "澳大利亚 奔富 BIN2 西拉子慕合怀特葡萄酒 750ml*6瓶【整箱装】\t\t ",
        "price": "999 元"
    }, {
        "index": 33,
        "title": "品味之旅",
        "src": "http://img0.gjw.com/Famous/2019/0803/1252e68c067e43dea74d41cdb88027ad.jpg",
        "text": "夜线 威士忌 700ml\t\t ",
        "price": "39 元"
    }, {
        "index": 34,
        "title": "正品行货",
        "src": "http://img0.gjw.com/Famous/2019/0803/9d0ea5bc06d548f38075dae37e23342a.jpg",
        "text": "英国 芝华士 12年威士忌 700ml\t\t ",
        "price": "172 元"
    }, {
        "index": 35,
        "title": "法式洋酒",
        "src": "http://img0.gjw.com/Famous/2019/0803/930416b74c864e54ba0d3e182118668f.jpg",
        "text": "法国 君度 力娇酒（配制酒） 700ml\t\t ",
        "price": "96 元"
    }, {
        "index": 36,
        "title": "带盒带码",
        "src": "http://img0.gjw.com/Famous/2019/0803/c2c566a7e3d843088dc89db79eb103db.jpg",
        "text": "英国 尊尼获加Johnnie Walker 黑牌威士忌黑方 700ml 带盒带码\t\t ",
        "price": "198 元"
    }







    , {
        "index": 37,
        "title": "95 人好评",
        "src": "http://img0.gjw.com/famous/2019/0717/b36b095b38e044529400a20128aa82d0.jpg",
        "text": "53度茅台飞天迎宾酒（ 2018年产）500ml  ",
        "price": "509 元"
    }, {
        "index": 38,
        "title": "19 人好评",
        "src": "http://img0.gjw.com/famous/2019/0717/92d4418365ad45d1bd5cdc4aed38f3a9.jpg",
        "text": "52度五粮窖龄酒20年500ml",
        "price": "376 元"
    }, {
        "index": 39,
        "title": "5 人好评",
        "src": "http://img0.gjw.com/famous/2019/0717/d12f2725eb634b53b206a2a7e7e2c18e.jpg",
        "text": "52度泸州老窖精品特曲限量珍藏版（ 2010年产）500ml",
        "price": "349 元"
    }, {
        "index": 49,
        "title": "8 人好评",
        "src": "http://img0.gjw.com/famous/2019/0717/1cbbb59e96464648b3508c77cfacd101.jpg",
        "text": "53度习酒醇酱500ml（2014年产）",
        "price": "298 元"
    }, {
        "index": 41,
        "title": "1 人好评",
        "src": "http://img0.gjw.com/famous/2019/0717/5365ab66d1dd4b07bc2258657844edad.jpg",
        "text": "52度泸州老窖老窖老酒( 2011年产) 500ml",
        "price": "89 元"
    }

]